isomer-1.0.0-py3.6-nspkg.pth
dev/Nightshift_css.json
dev/__init__.py
dev/isomer_client.py
dev/client/__init__.py
dev/templates/__init__.py
dev/templates/component.py.template
dev/templates/controller.js.template
dev/templates/index.js.template
dev/templates/init.py.template
dev/templates/isomer.service
dev/templates/nginx.conf
dev/templates/package.json.template
dev/templates/schemata.py.template
dev/templates/setup.py.template
dev/templates/view.html.template
dev/upright/isomer_agplv3.tpl
dev/upright/isomer_config.json
dev/upright/isomer_gplv3.tpl
isomer/component.py
isomer/database.py
isomer/debugger.py
isomer/iso.py
isomer/launcher.py
isomer/logger.py
isomer/migration.py
isomer/scm_version.py
isomer/version.py
isomer/events/__init__.py
isomer/events/client.py
isomer/events/objectmanager.py
isomer/events/schemamanager.py
isomer/events/system.py
isomer/misc/__init__.py
isomer/misc/path.py
isomer/provisions/__init__.py
isomer/provisions/base.py
isomer/provisions/system.py
isomer/provisions/user.py
isomer/schemata/__init__.py
isomer/schemata/base.py
isomer/schemata/client.py
isomer/schemata/component.py
isomer/schemata/defaultform.py
isomer/schemata/extends.py
isomer/schemata/geometry.py
isomer/schemata/logmessage.py
isomer/schemata/profile.py
isomer/schemata/system.py
isomer/schemata/tag.py
isomer/schemata/user.py
isomer/tool/__init__.py
isomer/tool/backup.py
isomer/tool/cli.py
isomer/tool/configuration.py
isomer/tool/create_module.py
isomer/tool/database.py
isomer/tool/defaults.py
isomer/tool/environment.py
isomer/tool/etc.py
isomer/tool/installer.py
isomer/tool/instance.py
isomer/tool/misc.py
isomer/tool/objects.py
isomer/tool/rbac.py
isomer/tool/remote.py
isomer/tool/system.py
isomer/tool/templates.py
isomer/tool/tool.py
isomer/tool/user.py
isomer/ui/__init__.py
isomer/ui/activitymonitor.py
isomer/ui/auth.py
isomer/ui/builder.py
isomer/ui/clientmanager.py
isomer/ui/clientobjects.py
isomer/ui/configurator.py
isomer/ui/objectmanager.py
isomer/ui/schemamanager.py
isomer-1.0.0.dist-info/LICENSE
isomer-1.0.0.dist-info/METADATA
isomer-1.0.0.dist-info/WHEEL
isomer-1.0.0.dist-info/dependency_links.txt
isomer-1.0.0.dist-info/entry_points.txt
isomer-1.0.0.dist-info/namespace_packages.txt
isomer-1.0.0.dist-info/top_level.txt
isomer-1.0.0.dist-info/RECORD
